emptycopy/__init__.py
emptycopy/cli.py
emptycopy-0.1.3.dist-info/LICENSE
emptycopy-0.1.3.dist-info/METADATA
emptycopy-0.1.3.dist-info/WHEEL
emptycopy-0.1.3.dist-info/entry_points.txt
emptycopy-0.1.3.dist-info/RECORD
