Metadata-Version: 2.1
Name: emptycopy
Version: 0.1.3
Summary: A CLI-tool for creating a complete copy of a directory and all it's subdirectories but with all files empty.
License: GPL-3.0-or-later
Author: Josef Anhede
Author-email: josefanhede@gmail.com
Requires-Python: >=3.10,<4.0
Classifier: License :: OSI Approved :: GNU General Public License v3 or later (GPLv3+)
Classifier: Programming Language :: Python :: 3
Classifier: Programming Language :: Python :: 3.10
Classifier: Programming Language :: Python :: 3.11
Classifier: Programming Language :: Python :: 3.12
Classifier: Programming Language :: Python :: 3.13
Requires-Dist: click (>=8.1.7,<9.0.0)
